labeller/__main__.py
labeller/createLabeller.py
labeller/htmlElements.py
labeller/resources/about.html
labeller/resources/app.py
labeller/resources/dashboard.css
labeller/resources/favicon.ico
labeller/resources/index.html
labeller/resources/labels.html
labeller/resources/navbar.html
labeller-0.2.0.dist-info/LICENSE
labeller-0.2.0.dist-info/METADATA
labeller-0.2.0.dist-info/WHEEL
labeller-0.2.0.dist-info/top_level.txt
labeller-0.2.0.dist-info/RECORD
