Metadata-Version: 2.1
Name: labeller
Version: 0.2.0
Summary: Create image labelling software for machine learning applications.
Home-page: https://github.com/mdbloice/Labeller
Author: Marcus D. Bloice
Author-email: marcus.bloice@medunigraz.at
License: MIT
Classifier: Development Status :: 4 - Beta
Classifier: Natural Language :: English
Classifier: License :: OSI Approved :: MIT License
Classifier: Operating System :: OS Independent
Classifier: Programming Language :: Python
Classifier: Programming Language :: Python :: 3
Classifier: Programming Language :: Python :: 3.6
Classifier: Programming Language :: Python :: 3.7
Classifier: Programming Language :: Python :: 3.8
Classifier: Programming Language :: Python :: 3.9
License-File: LICENSE
Requires-Dist: flask (>=2.0)
Requires-Dist: flask-bootstrap (>=3.3)
